notion_params/__init__.py
notion_params/client.py
notion_params/markdown.py
notion_params-0.0.6.dist-info/LICENSE
notion_params-0.0.6.dist-info/METADATA
notion_params-0.0.6.dist-info/WHEEL
notion_params-0.0.6.dist-info/top_level.txt
notion_params-0.0.6.dist-info/RECORD
