Metadata-Version: 2.1
Name: notion-params
Version: 0.0.6
Summary: Helper to build Notion API params, parse markdown text into Notion API blocks
Home-page: https://github.com/zhaowb/notion-params.git
Author: Wenbo Zhao
Author-email: zhaowb@gmail.com
License: UNKNOWN
Platform: UNKNOWN
Classifier: Programming Language :: Python :: 3
Classifier: License :: OSI Approved :: MIT License
Classifier: Operating System :: OS Independent
Requires-Python: >=3.6
License-File: LICENSE
Requires-Dist: marko (==1.2.0)
Requires-Dist: pydash
Requires-Dist: requests
Requires-Dist: backoff
